nano/__init__.py
nano/agent.py
nano/cli.py
nano/tools.py
nano/utils.py
nano_agent-4.0.1.dist-info/METADATA
nano_agent-4.0.1.dist-info/WHEEL
nano_agent-4.0.1.dist-info/entry_points.txt
nano_agent-4.0.1.dist-info/top_level.txt
nano_agent-4.0.1.dist-info/RECORD
