Metadata-Version: 2.4
Name: nano-agent
Version: 4.0.1
Summary: Nano: A minimal, zero-frills coding-agent for research on agent-in-the-loop training
Home-page: https://github.com/ASSERT-KTH/nano-agent
Author: Bjarni Haukur
Author-email: bjarnihaukur11@gmail.com
Classifier: Programming Language :: Python :: 3
Classifier: License :: OSI Approved :: MIT License
Classifier: Operating System :: OS Independent
Requires-Python: >=3.9
Requires-Dist: litellm>=1.73.0
Provides-Extra: test
Requires-Dist: GitPython>=3.1.0; extra == "test"
Dynamic: author
Dynamic: author-email
Dynamic: classifier
Dynamic: description
Dynamic: description-content-type
Dynamic: home-page
Dynamic: provides-extra
Dynamic: requires-dist
Dynamic: requires-python
Dynamic: summary
